object_store/__init__.py
object_store/aws_s3.py
object_store/azure.py
object_store/min_io.py
object_store/object_storage.py
object_store/object_storage_creator.py
object_store/object_storage_type.py
object_store/version.py
object_store-0.1.0.dist-info/LICENSE
object_store-0.1.0.dist-info/METADATA
object_store-0.1.0.dist-info/WHEEL
object_store-0.1.0.dist-info/top_level.txt
object_store-0.1.0.dist-info/zip-safe
object_store-0.1.0.dist-info/RECORD
