Metadata-Version: 2.1
Name: object-store
Version: 0.1.0
Summary: Python library for different object storages that have common methods.
Home-page: https://github.com/xlab-si/python-object-store-library
Author: XLAB d.o.o.
Author-email: pypi@xlab.si
License: UNKNOWN
Project-URL: Source Code, https://github.com/xlab-si/python-object-store-library
Project-URL: Bug Tracker, https://github.com/xlab-si/python-object-store-library/issues
Keywords: library,object store,python,aws,s3,azure,minio,bucket,container
Platform: UNKNOWN
Classifier: Development Status :: 2 - Pre-Alpha
Classifier: Environment :: Console
Classifier: Intended Audience :: Developers
Classifier: Intended Audience :: System Administrators
Classifier: License :: OSI Approved :: Apache Software License
Classifier: Operating System :: OS Independent
Classifier: Programming Language :: Python
Classifier: Programming Language :: Python :: 3
Classifier: Programming Language :: Python :: 3.6
Classifier: Programming Language :: Python :: 3.7
Requires-Dist: minio (==5.0.4)
Requires-Dist: boto3 (==1.10.9)
Requires-Dist: azure (==4.0.0)
Requires-Dist: azure-storage (==0.36.0)
